smlmlab/__init__.py
smlmlab/_widget.py
smlmlab/gui.py
smlmlab/gui.ui
smlmlab/napari.yaml
smlmlab/_tests/__init__.py
smlmlab/_tests/test_widget.py
smlmlab/utils/__init__.py
smlmlab/utils/compute_utils.py
smlmlab/utils/events_utils.py
smlmlab/utils/import_utils.py
smlmlab/utils/loc_utils.py
smlmlab/utils/picasso_utils.py
smlmlab/utils/plot_utils.py
smlmlab/utils/undrift_utils.py
smlmlab/utils/viewer_utils.py
napari_SMLMLAB-0.1.4.dist-info/LICENSE
napari_SMLMLAB-0.1.4.dist-info/METADATA
napari_SMLMLAB-0.1.4.dist-info/WHEEL
napari_SMLMLAB-0.1.4.dist-info/entry_points.txt
napari_SMLMLAB-0.1.4.dist-info/top_level.txt
napari_SMLMLAB-0.1.4.dist-info/RECORD
