Metadata-Version: 2.1
Name: napari-SMLMLAB
Version: 0.1.4
Summary: Napari widget for BP04 Practical.
Home-page: https://github.com/piedrro/napari-SMLMLAB
Author: Piers Turner
Author-email: Piers Turner <piers.turner@physics.ox.ac.uk>
License: 
Project-URL: Homepage, https://github.com/piedrro/napari-bacseg
Project-URL: Bug Tracker, https://github.com/piedrro/napari-bacseg/issues
Classifier: Framework :: napari
Classifier: Environment :: Plugins
Classifier: License :: OSI Approved :: BSD License
Classifier: Programming Language :: Python :: 3.9
Classifier: Operating System :: OS Independent
Requires-Python: >=3.9
License-File: LICENSE
Requires-Dist: napari[all]==0.5.0
Requires-Dist: numpy
Requires-Dist: magicgui
Requires-Dist: qtpy
Requires-Dist: scipy
Requires-Dist: pyqtgraph
Requires-Dist: picassosr==0.7.3
Requires-Dist: matplotlib
Requires-Dist: tqdm
Requires-Dist: pyqt5-tools
Requires-Dist: trackpy
Provides-Extra: testing
Requires-Dist: tox; extra == "testing"
Requires-Dist: pytest; extra == "testing"
Requires-Dist: pytest-cov; extra == "testing"
Requires-Dist: pytest-qt; extra == "testing"
Requires-Dist: napari; extra == "testing"
Requires-Dist: pyqt5; extra == "testing"
